{"note":"This file is an internal implementation detail to speed up HTML report generation. Its format can change at any time. You might be looking for the JSON report: https://coverage.rtfd.io/cmd.html#cmd-json","format":5,"version":"7.9.2","globals":"cffce140233eb77f2559d3182fa1beab","files":{"z_63aee5f6be5517ca___init___py":{"hash":"3c77fc9ef7f887ac2508d4109cf92472","index":{"url":"z_63aee5f6be5517ca___init___py.html","file":"robustML/__init__.py","description":"","nums":{"precision":0,"n_files":1,"n_statements":0,"n_excluded":0,"n_missing":0,"n_branches":0,"n_partial_branches":0,"n_missing_branches":0}}},"z_4b578eb7c81dd30e___init___py":{"hash":"3c77fc9ef7f887ac2508d4109cf92472","index":{"url":"z_4b578eb7c81dd30e___init___py.html","file":"robustML/advertrain/__init__.py","description":"","nums":{"precision":0,"n_files":1,"n_statements":0,"n_excluded":0,"n_missing":0,"n_branches":0,"n_partial_branches":0,"n_missing_branches":0}}},"z_4b578eb7c81dd30e_constants_py":{"hash":"d29b34e18fa3fc1025ceab35ec02de97","index":{"url":"z_4b578eb7c81dd30e_constants_py.html","file":"robustML/advertrain/constants.py","description":"","nums":{"precision":0,"n_files":1,"n_statements":6,"n_excluded":0,"n_missing":0,"n_branches":0,"n_partial_branches":0,"n_missing_branches":0}}},"z_3e179d03768015bc___init___py":{"hash":"3c77fc9ef7f887ac2508d4109cf92472","index":{"url":"z_3e179d03768015bc___init___py.html","file":"robustML/advertrain/dependencies/__init__.py","description":"","nums":{"precision":0,"n_files":1,"n_statements":0,"n_excluded":0,"n_missing":0,"n_branches":0,"n_partial_branches":0,"n_missing_branches":0}}},"z_3e179d03768015bc_autoattack_py":{"hash":"30b156d8f5c468ec11788b3ef9bbd033","index":{"url":"z_3e179d03768015bc_autoattack_py.html","file":"robustML/advertrain/dependencies/autoattack.py","description":"","nums":{"precision":0,"n_files":1,"n_statements":360,"n_excluded":0,"n_missing":314,"n_branches":0,"n_partial_branches":0,"n_missing_branches":0}}},"z_bdad8fe5ce1d9e50___init___py":{"hash":"3c77fc9ef7f887ac2508d4109cf92472","index":{"url":"z_bdad8fe5ce1d9e50___init___py.html","file":"robustML/advertrain/dependencies/cleverhans/__init__.py","description":"","nums":{"precision":0,"n_files":1,"n_statements":0,"n_excluded":0,"n_missing":0,"n_branches":0,"n_partial_branches":0,"n_missing_branches":0}}},"z_bdad8fe5ce1d9e50_fast_gradient_method_py":{"hash":"d51ef7aa5ea8e6276db376e7db0e3729","index":{"url":"z_bdad8fe5ce1d9e50_fast_gradient_method_py.html","file":"robustML/advertrain/dependencies/cleverhans/fast_gradient_method.py","description":"","nums":{"precision":0,"n_files":1,"n_statements":33,"n_excluded":0,"n_missing":10,"n_branches":0,"n_partial_branches":0,"n_missing_branches":0}}},"z_bdad8fe5ce1d9e50_projected_gradient_descent_py":{"hash":"db65e0e4973c2a56fe4fa3d25ad0228d","index":{"url":"z_bdad8fe5ce1d9e50_projected_gradient_descent_py.html","file":"robustML/advertrain/dependencies/cleverhans/projected_gradient_descent.py","description":"","nums":{"precision":0,"n_files":1,"n_statements":29,"n_excluded":0,"n_missing":2,"n_branches":0,"n_partial_branches":0,"n_missing_branches":0}}},"z_bdad8fe5ce1d9e50_utils_py":{"hash":"28df34de69740ec188ffd0a26ad75333","index":{"url":"z_bdad8fe5ce1d9e50_utils_py.html","file":"robustML/advertrain/dependencies/cleverhans/utils.py","description":"","nums":{"precision":0,"n_files":1,"n_statements":43,"n_excluded":0,"n_missing":14,"n_branches":0,"n_partial_branches":0,"n_missing_branches":0}}},"z_3e179d03768015bc_dropblock_py":{"hash":"7da3bfc80f17c498f4348883d39d04e9","index":{"url":"z_3e179d03768015bc_dropblock_py.html","file":"robustML/advertrain/dependencies/dropblock.py","description":"","nums":{"precision":0,"n_files":1,"n_statements":62,"n_excluded":0,"n_missing":13,"n_branches":0,"n_partial_branches":0,"n_missing_branches":0}}},"z_3e179d03768015bc_fire_py":{"hash":"cb158beb741346cbc5c3167bd747ee68","index":{"url":"z_3e179d03768015bc_fire_py.html","file":"robustML/advertrain/dependencies/fire.py","description":"","nums":{"precision":0,"n_files":1,"n_statements":70,"n_excluded":0,"n_missing":21,"n_branches":0,"n_partial_branches":0,"n_missing_branches":0}}},"z_3e179d03768015bc_trades_py":{"hash":"d9cbd296138dc6ba0ec7a65d53a09692","index":{"url":"z_3e179d03768015bc_trades_py.html","file":"robustML/advertrain/dependencies/trades.py","description":"","nums":{"precision":0,"n_files":1,"n_statements":56,"n_excluded":0,"n_missing":23,"n_branches":0,"n_partial_branches":0,"n_missing_branches":0}}},"z_4b578eb7c81dd30e_metrics_py":{"hash":"5c1fda24f068b91dc646376b2d0bbb88","index":{"url":"z_4b578eb7c81dd30e_metrics_py.html","file":"robustML/advertrain/metrics.py","description":"","nums":{"precision":0,"n_files":1,"n_statements":53,"n_excluded":0,"n_missing":10,"n_branches":0,"n_partial_branches":0,"n_missing_branches":0}}},"z_4b578eb7c81dd30e_models_py":{"hash":"c19cf978eae2ddb1167c058fdfb64ef6","index":{"url":"z_4b578eb7c81dd30e_models_py.html","file":"robustML/advertrain/models.py","description":"","nums":{"precision":0,"n_files":1,"n_statements":198,"n_excluded":0,"n_missing":114,"n_branches":0,"n_partial_branches":0,"n_missing_branches":0}}},"z_f9f01431d5b8aa80___init___py":{"hash":"3c77fc9ef7f887ac2508d4109cf92472","index":{"url":"z_f9f01431d5b8aa80___init___py.html","file":"robustML/advertrain/training/__init__.py","description":"","nums":{"precision":0,"n_files":1,"n_statements":0,"n_excluded":0,"n_missing":0,"n_branches":0,"n_partial_branches":0,"n_missing_branches":0}}},"z_f9f01431d5b8aa80_adversarial_training_py":{"hash":"fb60518f38c8c87fad26a349bae90cbb","index":{"url":"z_f9f01431d5b8aa80_adversarial_training_py.html","file":"robustML/advertrain/training/adversarial_training.py","description":"","nums":{"precision":0,"n_files":1,"n_statements":16,"n_excluded":0,"n_missing":3,"n_branches":0,"n_partial_branches":0,"n_missing_branches":0}}},"z_f9f01431d5b8aa80_autoattack_training_py":{"hash":"f31df1d37e7db7eec20c813266629345","index":{"url":"z_f9f01431d5b8aa80_autoattack_training_py.html","file":"robustML/advertrain/training/autoattack_training.py","description":"","nums":{"precision":0,"n_files":1,"n_statements":13,"n_excluded":0,"n_missing":2,"n_branches":0,"n_partial_branches":0,"n_missing_branches":0}}},"z_f9f01431d5b8aa80_classical_training_py":{"hash":"d4628a5c620a310de8f8d919a8f6805c","index":{"url":"z_f9f01431d5b8aa80_classical_training_py.html","file":"robustML/advertrain/training/classical_training.py","description":"","nums":{"precision":0,"n_files":1,"n_statements":76,"n_excluded":0,"n_missing":52,"n_branches":0,"n_partial_branches":0,"n_missing_branches":0}}},"z_f9f01431d5b8aa80_fire_training_py":{"hash":"67433f34270259eb22e67c81a1976e7e","index":{"url":"z_f9f01431d5b8aa80_fire_training_py.html","file":"robustML/advertrain/training/fire_training.py","description":"","nums":{"precision":0,"n_files":1,"n_statements":30,"n_excluded":0,"n_missing":11,"n_branches":0,"n_partial_branches":0,"n_missing_branches":0}}},"z_4b578eb7c81dd30e_transforms_py":{"hash":"f826ae37cd0e8c287acfcb844c706944","index":{"url":"z_4b578eb7c81dd30e_transforms_py.html","file":"robustML/advertrain/transforms.py","description":"","nums":{"precision":0,"n_files":1,"n_statements":9,"n_excluded":0,"n_missing":0,"n_branches":0,"n_partial_branches":0,"n_missing_branches":0}}},"z_4e2504d3680fac65_test_autoattack_py":{"hash":"0b6b86e33935e573a143ec73e3cd83e7","index":{"url":"z_4e2504d3680fac65_test_autoattack_py.html","file":"tests/tests_advertrain/test_dependencies/test_autoattack.py","description":"","nums":{"precision":0,"n_files":1,"n_statements":16,"n_excluded":0,"n_missing":1,"n_branches":0,"n_partial_branches":0,"n_missing_branches":0}}},"z_2d8a365c8dd07308_test_fast_gradient_method_py":{"hash":"fc1bd5b237d841421e4d55f39f9e3e08","index":{"url":"z_2d8a365c8dd07308_test_fast_gradient_method_py.html","file":"tests/tests_advertrain/test_dependencies/test_cleverhans/test_fast_gradient_method.py","description":"","nums":{"precision":0,"n_files":1,"n_statements":19,"n_excluded":0,"n_missing":0,"n_branches":0,"n_partial_branches":0,"n_missing_branches":0}}},"z_2d8a365c8dd07308_test_projected_gradient_descent_py":{"hash":"dfa596e1e0b62b0edc710c487f5c9963","index":{"url":"z_2d8a365c8dd07308_test_projected_gradient_descent_py.html","file":"tests/tests_advertrain/test_dependencies/test_cleverhans/test_projected_gradient_descent.py","description":"","nums":{"precision":0,"n_files":1,"n_statements":41,"n_excluded":0,"n_missing":0,"n_branches":0,"n_partial_branches":0,"n_missing_branches":0}}},"z_2d8a365c8dd07308_test_utils_py":{"hash":"21b986a3423b2962429d66aeb8b24cd9","index":{"url":"z_2d8a365c8dd07308_test_utils_py.html","file":"tests/tests_advertrain/test_dependencies/test_cleverhans/test_utils.py","description":"","nums":{"precision":0,"n_files":1,"n_statements":42,"n_excluded":0,"n_missing":0,"n_branches":0,"n_partial_branches":0,"n_missing_branches":0}}},"z_4e2504d3680fac65_test_dropblock_py":{"hash":"5af5fdbff37557afff4c896ae7d2ecd0","index":{"url":"z_4e2504d3680fac65_test_dropblock_py.html","file":"tests/tests_advertrain/test_dependencies/test_dropblock.py","description":"","nums":{"precision":0,"n_files":1,"n_statements":33,"n_excluded":0,"n_missing":0,"n_branches":0,"n_partial_branches":0,"n_missing_branches":0}}},"z_4e2504d3680fac65_test_fire_py":{"hash":"931fd1096dca1cd374ac9e8cb0ad009e","index":{"url":"z_4e2504d3680fac65_test_fire_py.html","file":"tests/tests_advertrain/test_dependencies/test_fire.py","description":"","nums":{"precision":0,"n_files":1,"n_statements":32,"n_excluded":0,"n_missing":0,"n_branches":0,"n_partial_branches":0,"n_missing_branches":0}}},"z_4e2504d3680fac65_test_trades_py":{"hash":"50b4593ba139527496dfd8ed571a48de","index":{"url":"z_4e2504d3680fac65_test_trades_py.html","file":"tests/tests_advertrain/test_dependencies/test_trades.py","description":"","nums":{"precision":0,"n_files":1,"n_statements":28,"n_excluded":0,"n_missing":0,"n_branches":0,"n_partial_branches":0,"n_missing_branches":0}}},"z_de1d2034512030eb_test_metrics_py":{"hash":"9e5c19534de99d2f44163191cccbc364","index":{"url":"z_de1d2034512030eb_test_metrics_py.html","file":"tests/tests_advertrain/test_metrics.py","description":"","nums":{"precision":0,"n_files":1,"n_statements":35,"n_excluded":0,"n_missing":0,"n_branches":0,"n_partial_branches":0,"n_missing_branches":0}}},"z_de1d2034512030eb_test_models_py":{"hash":"bc11f81285828e30dbf1065cf65a6717","index":{"url":"z_de1d2034512030eb_test_models_py.html","file":"tests/tests_advertrain/test_models.py","description":"","nums":{"precision":0,"n_files":1,"n_statements":56,"n_excluded":0,"n_missing":0,"n_branches":0,"n_partial_branches":0,"n_missing_branches":0}}},"z_9207188b405325c8_test_adversarial_training_py":{"hash":"1832592c61b925f17d4ed2af45ea068d","index":{"url":"z_9207188b405325c8_test_adversarial_training_py.html","file":"tests/tests_advertrain/test_training/test_adversarial_training.py","description":"","nums":{"precision":0,"n_files":1,"n_statements":33,"n_excluded":0,"n_missing":1,"n_branches":0,"n_partial_branches":0,"n_missing_branches":0}}},"z_9207188b405325c8_test_autoattack_training_py":{"hash":"115900e907feca8eb46d8d3193192694","index":{"url":"z_9207188b405325c8_test_autoattack_training_py.html","file":"tests/tests_advertrain/test_training/test_autoattack_training.py","description":"","nums":{"precision":0,"n_files":1,"n_statements":29,"n_excluded":0,"n_missing":1,"n_branches":0,"n_partial_branches":0,"n_missing_branches":0}}},"z_9207188b405325c8_test_classical_training_py":{"hash":"b712eaa743a65acf7e2090b510c8c1e3","index":{"url":"z_9207188b405325c8_test_classical_training_py.html","file":"tests/tests_advertrain/test_training/test_classical_training.py","description":"","nums":{"precision":0,"n_files":1,"n_statements":37,"n_excluded":0,"n_missing":5,"n_branches":0,"n_partial_branches":0,"n_missing_branches":0}}},"z_9207188b405325c8_test_fire_training_py":{"hash":"5acba2150c4f9aa24ac81d53c4677768","index":{"url":"z_9207188b405325c8_test_fire_training_py.html","file":"tests/tests_advertrain/test_training/test_fire_training.py","description":"","nums":{"precision":0,"n_files":1,"n_statements":30,"n_excluded":0,"n_missing":0,"n_branches":0,"n_partial_branches":0,"n_missing_branches":0}}},"z_de1d2034512030eb_test_transforms_py":{"hash":"34726c0f1d0202a9d2fe51d8113d6b51","index":{"url":"z_de1d2034512030eb_test_transforms_py.html","file":"tests/tests_advertrain/test_transforms.py","description":"","nums":{"precision":0,"n_files":1,"n_statements":26,"n_excluded":0,"n_missing":0,"n_branches":0,"n_partial_branches":0,"n_missing_branches":0}}}}}